{
    "name": "Mi Gym",
    "short_name": "Mi Gym",
    "description": "Accede a tu gimnasio desde tu móvil",
    "start_url": "/app/",
    "display": "standalone",
    "background_color": "#f8fafc",
    "theme_color": "#4F46E5",
    "orientation": "portrait-primary",
    "scope": "/app/",
    "icons": [
        {
            "src": "/static/icons/portal/icon-72.png",
            "sizes": "72x72",
            "type": "image/png"
        },
        {
            "src": "/static/icons/portal/icon-96.png",
            "sizes": "96x96",
            "type": "image/png"
        },
        {
            "src": "/static/icons/portal/icon-128.png",
            "sizes": "128x128",
            "type": "image/png"
        },
        {
            "src": "/static/icons/portal/icon-144.png",
            "sizes": "144x144",
            "type": "image/png"
        },
        {
            "src": "/static/icons/portal/icon-152.png",
            "sizes": "152x152",
            "type": "image/png"
        },
        {
            "src": "/static/icons/portal/icon-192.png",
            "sizes": "192x192",
            "type": "image/png",
            "purpose": "any maskable"
        },
        {
            "src": "/static/icons/portal/icon-384.png",
            "sizes": "384x384",
            "type": "image/png"
        },
        {
            "src": "/static/icons/portal/icon-512.png",
            "sizes": "512x512",
            "type": "image/png",
            "purpose": "any maskable"
        }
    ],
    "categories": [
        "health",
        "fitness",
        "lifestyle"
    ],
    "shortcuts": [
        {
            "name": "Reservar clase",
            "short_name": "Reservar",
            "description": "Reserva tu próxima clase",
            "url": "/app/bookings/",
            "icons": [
                {
                    "src": "/static/icons/portal/icon-96.png",
                    "sizes": "96x96"
                }
            ]
        },
        {
            "name": "Mi perfil",
            "short_name": "Perfil",
            "description": "Ver mi perfil",
            "url": "/app/profile/",
            "icons": [
                {
                    "src": "/static/icons/portal/icon-96.png",
                    "sizes": "96x96"
                }
            ]
        }
    ]
}